etiq_core.cp39-win_amd64.pyd
etiq_core.pyi
etiq_core/sample_data/DefaultLogisticRegression.pkl
etiq_core/sample_data/DefaultRandomForest.pkl
etiq_core/sample_data/DefaultXGBClassifier.pkl
etiq_core/sample_data/adult_data_sampled.pkl
etiq_core/sample_data/adult_protected_train_resampled.pkl
etiq_core/sample_data/adult_x_train_resampled.pkl
etiq_core/sample_data/adult_y_train_resampled.pkl
etiq_core/sample_data/adultdata.pkl
etiq_core/sample_data/adultdataset.csv
etiq_core/sample_data/encoded_adult.pkl
etiq_core-1.2.4.dist-info/LICENSE
etiq_core-1.2.4.dist-info/METADATA
etiq_core-1.2.4.dist-info/WHEEL
etiq_core-1.2.4.dist-info/top_level.txt
etiq_core-1.2.4.dist-info/RECORD
