Metadata-Version: 2.1
Name: etiq-core
Version: 1.2.4
Summary: ETIQ.ai debiasing library
Home-page: https://etiq.ai/
Author: ETIQ AI
Author-email: devops@etiq.ai
License: UNKNOWN
Keywords: ai,bias,etiq,fairness
Platform: UNKNOWN
Classifier: Development Status :: 5 - Production/Stable
Classifier: Environment :: Console
Classifier: Environment :: MacOS X
Classifier: Environment :: Win32 (MS Windows)
Classifier: Framework :: IPython
Classifier: Framework :: Jupyter
Classifier: Intended Audience :: Science/Research
Classifier: License :: Other/Proprietary License
Classifier: Natural Language :: English
Classifier: Programming Language :: Python :: 3.6
Classifier: Programming Language :: Python :: 3.7
Classifier: Programming Language :: Python :: 3.8
Classifier: Programming Language :: Python :: 3.9
Classifier: Topic :: Scientific/Engineering
Classifier: Topic :: Scientific/Engineering :: Artificial Intelligence
Classifier: Topic :: Scientific/Engineering :: Information Analysis
Requires-Dist: platformdirs
Requires-Dist: numpy
Requires-Dist: pandas
Requires-Dist: sqlalchemy (>=1.4)
Requires-Dist: scikit-learn
Requires-Dist: xgboost
Requires-Dist: requests
Requires-Dist: factory-boy
Requires-Dist: dataclasses ; python_version == "3.6"
